{"variants":{"facing=east,in_wall=false,open=false":{"model":"tfaura:block/wood/fence_gate/ancient","y":270,"uvlock":true},"facing=north,in_wall=false,open=false":{"model":"tfaura:block/wood/fence_gate/ancient","y":180,"uvlock":true},"facing=south,in_wall=false,open=false":{"model":"tfaura:block/wood/fence_gate/ancient"},"facing=west,in_wall=false,open=false":{"model":"tfaura:block/wood/fence_gate/ancient","y":90,"uvlock":true},"facing=east,in_wall=false,open=true":{"model":"tfaura:block/wood/fence_gate/ancient_open","y":270,"uvlock":true},"facing=north,in_wall=false,open=true":{"model":"tfaura:block/wood/fence_gate/ancient_open","y":180,"uvlock":true},"facing=south,in_wall=false,open=true":{"model":"tfaura:block/wood/fence_gate/ancient_open"},"facing=west,in_wall=false,open=true":{"model":"tfaura:block/wood/fence_gate/ancient_open","y":90,"uvlock":true},"facing=east,in_wall=true,open=false":{"model":"tfaura:block/wood/fence_gate/ancient_wall","y":270,"uvlock":true},"facing=north,in_wall=true,open=false":{"model":"tfaura:block/wood/fence_gate/ancient_wall","y":180,"uvlock":true},"facing=south,in_wall=true,open=false":{"model":"tfaura:block/wood/fence_gate/ancient_wall"},"facing=west,in_wall=true,open=false":{"model":"tfaura:block/wood/fence_gate/ancient_wall","y":90,"uvlock":true},"facing=east,in_wall=true,open=true":{"model":"tfaura:block/wood/fence_gate/ancient_wall_open","y":270,"uvlock":true},"facing=north,in_wall=true,open=true":{"model":"tfaura:block/wood/fence_gate/ancient_wall_open","y":180,"uvlock":true},"facing=south,in_wall=true,open=true":{"model":"tfaura:block/wood/fence_gate/ancient_wall_open"},"facing=west,in_wall=true,open=true":{"model":"tfaura:block/wood/fence_gate/ancient_wall_open","y":90,"uvlock":true}}}
